{
  "name": "Infra Status Slash Command",
  "nodes": [
    {
      "parameters": {
        "httpMethod": "POST",
        "path": "infra-status",
        "responseMode": "responseNode",
        "options": {}
      },
      "id": "webhook-status",
      "name": "Webhook",
      "type": "n8n-nodes-base.webhook",
      "typeVersion": 2.1,
      "position": [250, 300]
    },
    {
      "parameters": {
        "jsCode": "const apiKey = $env.N8N_API_KEY;\nlet total = 0, active = 0, inactiveNames = [], liveness = '000';\n\ntry {\n  const resp = await this.helpers.httpRequest({\n    method: 'GET',\n    url: 'http://localhost:5678/api/v1/workflows?limit=250',\n    headers: { 'X-N8N-API-KEY': apiKey },\n  });\n  liveness = '200';\n  const workflows = resp.data || [];\n  total = workflows.length;\n  active = workflows.filter(w => w.active).length;\n  inactiveNames = workflows.filter(w => !w.active).map(w => w.name);\n} catch (e) {\n  // n8n REST API unreachable or auth failed\n}\n\nreturn [{\n  json: {\n    healthy: active === total && liveness === '200',\n    totalCount: total,\n    activeCount: active,\n    inactiveCount: total - active,\n    inactiveNames,\n    livenessStatus: liveness\n  }\n}];"
      },
      "id": "run-health-checks",
      "name": "Run Health Checks",
      "type": "n8n-nodes-base.code",
      "typeVersion": 2,
      "position": [500, 300]
    },
    {
      "parameters": {
        "jsCode": "const check = $input.first().json;\nconst now = new Date().toLocaleString('en-US', { timeZone: 'America/Los_Angeles', dateStyle: 'medium', timeStyle: 'short' });\n\nlet text = '';\nif (check.healthy) {\n  text = `:white_check_mark: *Infra Status* — ${now}\\n\\n• ${check.activeCount}/${check.totalCount} workflows active\\n• n8n reachable (${check.livenessStatus})\\n\\nAll systems operational.`;\n} else {\n  const parts = [`:warning: *Infra Status — ISSUES DETECTED* — ${now}\\n`];\n  parts.push(`• Workflows: ${check.activeCount}/${check.totalCount} active`);\n  if (check.inactiveNames && check.inactiveNames.length > 0) {\n    parts.push(`• Inactive: ${check.inactiveNames.join(', ')}`);\n  }\n  parts.push(`• n8n liveness: ${check.livenessStatus}`);\n  text = parts.join('\\n');\n}\n\nreturn [{ json: { response_type: 'in_channel', text } }];"
      },
      "id": "format-response",
      "name": "Format Response",
      "type": "n8n-nodes-base.code",
      "typeVersion": 2,
      "position": [750, 300]
    },
    {
      "parameters": {
        "respondWith": "firstIncomingItem",
        "options": {
          "responseCode": 200,
          "responseHeaders": {
            "entries": [
              { "name": "Content-Type", "value": "application/json" }
            ]
          }
        }
      },
      "id": "respond-status",
      "name": "Respond",
      "type": "n8n-nodes-base.respondToWebhook",
      "typeVersion": 1.5,
      "position": [1000, 300]
    }
  ],
  "connections": {
    "Webhook": {
      "main": [
        [
          { "node": "Run Health Checks", "type": "main", "index": 0 }
        ]
      ]
    },
    "Run Health Checks": {
      "main": [
        [
          { "node": "Format Response", "type": "main", "index": 0 }
        ]
      ]
    },
    "Format Response": {
      "main": [
        [
          { "node": "Respond", "type": "main", "index": 0 }
        ]
      ]
    }
  },
  "settings": { "executionOrder": "v1" },
  "staticData": null,
  "tags": [],
  "pinData": {},
  "id": "s1t2a3t4-u5s6-4s7l-8a9s-0h1c2m3d4s5l"
}
