{
  "state": "FL",
  "state_name": "Florida",
  "entity_type": "LLC",
  "sos_url": "https://dos.fl.gov/sunbiz/",
  "filing_office": "Florida Division of Corporations",
  "fees": {
    "standard": {
      "amount_cents": 12500,
      "description": "LLC Articles of Organization filing fee",
      "is_expedited": false,
      "processing_days": 3
    }
  },
  "filing": {
    "primary": {
      "method": "portal",
      "url": "https://dos.fl.gov/sunbiz/",
      "notes": "Florida Division of Corporations online filing"
    },
    "fallback": {
      "method": "mail",
      "url": "https://dos.fl.gov/sunbiz/",
      "notes": "Mail filing to Florida Division of Corporations"
    }
  },
  "requirements": {
    "articles_of_organization": true,
    "operating_agreement_required": false,
    "publication_required": false,
    "registered_agent_required": true,
    "annual_report_required": true,
    "annual_report_fee_cents": 13875,
    "franchise_tax": false
  },
  "processing": {
    "standard_days": 3
  },
  "naming": {
    "required_suffix": [
      "LLC",
      "L.L.C.",
      "Limited Liability Company"
    ],
    "restricted_words": [
      "Bank",
      "Insurance",
      "Trust"
    ]
  },
  "compliance": {
    "annual_report_due": "May 1"
  },
  "verification": {
    "last_verified": "2026-03-20T05:53:21.857Z",
    "sources": [
      {
        "name": "LLC Requirements by State (llcrequirements.com)",
        "url": "https://llcrequirements.com/",
        "accessed_at": "2026-03-20T05:53:21.857Z"
      },
      {
        "name": "Discern Franchise Tax by State",
        "url": "https://www.discern.com/resources/franchise-tax-information",
        "accessed_at": "2026-03-20T05:53:21.857Z"
      },
      {
        "name": "Florida Division of Corporations",
        "url": "https://dos.fl.gov/sunbiz/",
        "accessed_at": "2026-03-20T05:53:21.857Z"
      }
    ],
    "verified_by": "deterministic_parse",
    "confidence": 0.99
  }
}
